pysnaffler/__init__.py
pysnaffler/__main__.py
pysnaffler/_version.py
pysnaffler/ruleset.py
pysnaffler/scanner.py
pysnaffler/snaffler.py
pysnaffler/whatif.py
pysnaffler/rulefiles/__init__.py
pysnaffler/rules/__init__.py
pysnaffler/rules/constants.py
pysnaffler/rules/contents.py
pysnaffler/rules/directory.py
pysnaffler/rules/file.py
pysnaffler/rules/rule.py
pysnaffler/rules/share.py
pysnaffler/utils/__init__.py
pysnaffler-0.0.1.dist-info/METADATA
pysnaffler-0.0.1.dist-info/WHEEL
pysnaffler-0.0.1.dist-info/entry_points.txt
pysnaffler-0.0.1.dist-info/top_level.txt
pysnaffler-0.0.1.dist-info/RECORD
